pofy/__init__.py
pofy/loader.py
pofy/fields/__init__.py
pofy/fields/base_field.py
pofy/fields/bool_field.py
pofy/fields/dict_field.py
pofy/fields/enum_field.py
pofy/fields/float_field.py
pofy/fields/int_field.py
pofy/fields/list_field.py
pofy/fields/object_field.py
pofy/fields/path_field.py
pofy/fields/string_field.py
pofy/tag_handlers/__init__.py
pofy/tag_handlers/env_handler.py
pofy/tag_handlers/first_of_handler.py
pofy/tag_handlers/glob_handler.py
pofy/tag_handlers/if_handler.py
pofy/tag_handlers/import_handler.py
pofy/tag_handlers/merge_handler.py
pofy/tag_handlers/path_handler.py
pofy/tag_handlers/tag_handler.py
pofy-1.0.0.dist-info/LICENSE
pofy-1.0.0.dist-info/METADATA
pofy-1.0.0.dist-info/WHEEL
pofy-1.0.0.dist-info/top_level.txt
pofy-1.0.0.dist-info/RECORD
