Metadata-Version: 2.1
Name: pofy
Version: 1.0.0
Summary: Python Yaml Object deserializer based on PyYAML.
Home-page: http://github.com/an-otter-world/pofy/
Author: An Otter World
Author-email: an-otter-world@ki-dour.org
License: WTFPL
Keywords: YAML,serialization
Platform: UNKNOWN
Classifier: Development Status :: 3 - Alpha
Classifier: Intended Audience :: Developers
Classifier: Operating System :: OS Independent
Classifier: Programming Language :: Python
Classifier: Programming Language :: Python :: 3.8
Classifier: Programming Language :: Python :: Implementation :: CPython
Classifier: Programming Language :: Python :: Implementation :: PyPy
Classifier: Topic :: Software Development :: Libraries :: Python Modules
Classifier: Topic :: Text Processing :: Markup
Requires-Dist: pyyaml
